[{"id":"789567895785","name":"Example plant","dominant":"hybrid","amount":100,"thc":18.5,"cbd":2,"plantDate":{"epoch":1671044890240,"tz":"america/new_york","silent":true,"_weekStart":1,"_today":{}},"stage":"vegetation"},{"id":"789567895785","name":"Example plant","dominant":"hybrid","amount":100,"thc":18.5,"cbd":2,"plantDate":{"epoch":1671044890240,"tz":"america/new_york","silent":true,"_weekStart":1,"_today":{}},"stage":"vegetation"},{"id":"789567895785","name":"Example plant","dominant":"hybrid","amount":100,"thc":18.5,"cbd":2,"plantDate":{"epoch":1671045764239,"tz":"america/new_york","silent":true,"_weekStart":1,"_today":{}},"stage":"vegetation"},{"id":"789567895785","name":"Example plant","dominant":"sativa","amount":100,"thc":18.5,"cbd":2,"plantDate":{"epoch":1671045795910,"tz":"america/new_york","silent":true,"_weekStart":1,"_today":{}},"stage":"vegetation"},{"id":"789567895785","name":"Example plant","dominant":"indica","amount":100,"thc":18.5,"cbd":2,"plantDate":{"epoch":1671046752548,"tz":"america/new_york","silent":true,"_weekStart":1,"_today":{}},"stage":"vegetation"},{"id":"789567895785","name":"Example plant","dominant":"indica","amount":100,"thc":18.5,"cbd":2,"plantDate":{"epoch":1671052955609,"tz":"america/new_york","silent":true,"_weekStart":1,"_today":{}},"stage":"vegetation","seedType":"normal"},{"id":"789567895785","name":"Example plant","dominant":"indica","amount":100,"thc":18.5,"cbd":2,"plantDate":{"epoch":1671067475690,"tz":"america/new_york","silent":true,"_weekStart":1,"_today":{}},"stage":"vegetation","seedType":"normal"},{"id":"789567895785","name":"Example plant","dominant":"indica","amount":100,"thc":18.5,"cbd":2,"plantDate":{"epoch":1671072435916,"tz":"america/new_york","silent":true,"_weekStart":1,"_today":{}},"stage":"vegetation","seedType":"normal"},{"id":"789567895785","name":"Example plant","dominant":"indica","amount":100,"thc":18.5,"cbd":2,"plantDate":{"epoch":1671127012891,"tz":"america/new_york","silent":true,"_weekStart":1,"_today":{}},"stage":"vegetation","seedType":"normal"},{"id":"789567895785","name":"Example plant","dominant":"indica","amount":100,"thc":18.5,"cbd":2,"plantDate":{"epoch":1671242833918,"tz":"america/new_york","silent":true,"_weekStart":1,"_today":{}},"stage":"vegetation","seedType":"normal"},{"id":"789567895785","name":"Example plant","dominant":"indica","amount":100,"thc":18.5,"cbd":2,"plantDate":{"epoch":1671242931009,"tz":"america/new_york","silent":true,"_weekStart":1,"_today":{}},"stage":"vegetation","seedType":"normal"}]